LICENSE
poetryup/__init__.py
poetryup/core/cmd.py
poetryup/core/poetry.py
poetryup/core/pyproject.py
poetryup/main.py
poetryup/models/dependency.py
poetryup-0.12.7.dist-info/entry_points.txt
poetryup-0.12.7.dist-info/LICENSE
poetryup-0.12.7.dist-info/WHEEL
poetryup-0.12.7.dist-info/METADATA
poetryup-0.12.7.dist-info/RECORD
