Metadata-Version: 2.1
Name: poetryup
Version: 0.12.7
Summary: Update dependencies and bump their version in the pyproject.toml file
Home-page: https://github.com/MousaZeidBaker/poetryup
License: MIT
Keywords: packaging,dependency,poetry,poetryup
Author: Mousa Zeid Baker
Requires-Python: >=3.6,<4.0
Classifier: Development Status :: 5 - Production/Stable
Classifier: Development Status :: 7 - Inactive
Classifier: License :: OSI Approved :: MIT License
Classifier: Operating System :: OS Independent
Classifier: Programming Language :: Python :: 3
Classifier: Programming Language :: Python :: 3.6
Classifier: Programming Language :: Python :: 3.7
Classifier: Programming Language :: Python :: 3.8
Classifier: Programming Language :: Python :: 3.9
Classifier: Programming Language :: Python :: 3.10
Classifier: Programming Language :: Python :: 3
Requires-Dist: packaging (>=21.3,<22.0)
Requires-Dist: tomlkit (>=0.11.0,<0.12.0)
Requires-Dist: typer (>=0.4.1,<0.5.0)
Project-URL: Repository, https://github.com/MousaZeidBaker/poetryup
